.gitignore
.travis.yml
CHANGES.txt
MANIFEST.in
README.rst
bootstrap.py
buildout40.cfg
buildout41.cfg
buildout42.cfg
buildout43.cfg
setup.py
sources.cfg
docs/LICENSE.GPL
docs/LICENSE.txt
p4a/__init__.py
p4a/__init__.pyc
p4a.plonecalendar.egg-info/PKG-INFO
p4a.plonecalendar.egg-info/SOURCES.txt
p4a.plonecalendar.egg-info/dependency_links.txt
p4a.plonecalendar.egg-info/entry_points.txt
p4a.plonecalendar.egg-info/namespace_packages.txt
p4a.plonecalendar.egg-info/not-zip-safe
p4a.plonecalendar.egg-info/requires.txt
p4a.plonecalendar.egg-info/top_level.txt
p4a/plonecalendar/__init__.py
p4a/plonecalendar/calendar.py
p4a/plonecalendar/calendar.txt
p4a/plonecalendar/configure.zcml
p4a/plonecalendar/content.py
p4a/plonecalendar/eventprovider.py
p4a/plonecalendar/sitesetup.py
p4a/plonecalendar/subtype.py
p4a/plonecalendar/Extensions/Install.py
p4a/plonecalendar/Extensions/__init__.py
p4a/plonecalendar/browser/__init__.py
p4a/plonecalendar/browser/configure.zcml
p4a/plonecalendar/browser/datetime.xsl
p4a/plonecalendar/browser/eventfilter.py
p4a/plonecalendar/browser/icalendar.pt
p4a/plonecalendar/browser/icalendar.py
p4a/plonecalendar/browser/icalendar_import.pt
p4a/plonecalendar/browser/location_filter.pt
p4a/plonecalendar/browser/navigation.pt
p4a/plonecalendar/browser/support.py
p4a/plonecalendar/browser/uri.xsl
p4a/plonecalendar/browser/xhtml2vcal.xsl
p4a/plonecalendar/browser/resources/icon_import_ical.png
p4a/plonecalendar/locales/p4a.plonecalendar.pot
p4a/plonecalendar/locales/rebuild.sh
p4a/plonecalendar/locales/rebuild_i18n.log
p4a/plonecalendar/locales/es/LC_MESSAGES/p4a.plonecalendar.po
p4a/plonecalendar/profiles/default/metadata.xml
p4a/plonecalendar/profiles/default/types/Collection.xml
p4a/plonecalendar/profiles/default/types/Folder.xml
p4a/plonecalendar/profiles/default/types/Topic.xml
p4a/plonecalendar/tests/__init__.py
p4a/plonecalendar/tests/test_eventproviders.py
p4a/plonecalendar/tests/test_functional.py