Metadata-Version: 1.1
Name: p4a.plonecalendar
Version: 2.1
Summary: Plone4Artists calendar add-on for Plone
Home-page: https://github.com/collective/p4a.plonecalendar
Author: Rocky Burt
Author-email: rocky@serverzen.com
License: GPL
Keywords: Plone4Artists events event calendar calendaring
Platform: UNKNOWN
Classifier: Framework :: Zope2
Classifier: Framework :: Plone
Classifier: Framework :: Plone :: 4.0
Classifier: Framework :: Plone :: 4.1
Classifier: Framework :: Plone :: 4.2
Classifier: Framework :: Plone :: 4.3
Classifier: Programming Language :: Python
Classifier: Programming Language :: Python :: 2.6
Classifier: Programming Language :: Python :: 2.7
Classifier: License :: OSI Approved :: GNU General Public License (GPL)
Classifier: Topic :: Software Development :: Libraries :: Python Modules
